classroom_extensions/__init__.py
classroom_extensions/mariadb.py
classroom_extensions/mariadb_install.py
classroom_extensions/mongodb.py
classroom_extensions/mongodb_install.py
classroom_extensions/node_install.py
classroom_extensions/plantuml.py
classroom_extensions/util.py
classroom_extensions/web.py
classroom_extensions-0.0.14.dist-info/LICENSE
classroom_extensions-0.0.14.dist-info/METADATA
classroom_extensions-0.0.14.dist-info/WHEEL
classroom_extensions-0.0.14.dist-info/top_level.txt
classroom_extensions-0.0.14.dist-info/RECORD
