Metadata-Version: 2.2
Name: classroom_extensions
Version: 0.0.14
Summary: IPython extensions used for teaching
Author-email: Marcos Dias de Assuncao <assuncao@acm.org>
Maintainer-email: Marcos Dias de Assuncao <assuncao@acm.org>
License: MIT
Project-URL: Homepage, https://github.com/assuncaomarcos/classroom_extensions
Project-URL: Bug Reports, https://github.com/assuncaomarcos/classroom_extensions
Project-URL: Say Thanks!, https://saythanks.io/to/assuncaomarcos
Project-URL: Source, https://github.com/assuncaomarcos/classroom_extensions
Keywords: IPython,extensions,teaching
Classifier: Development Status :: 3 - Alpha
Classifier: Intended Audience :: Developers
Classifier: Intended Audience :: Information Technology
Classifier: Topic :: Scientific/Engineering
Classifier: Topic :: Software Development :: Libraries
Classifier: License :: OSI Approved :: MIT License
Classifier: Programming Language :: Python :: 3
Classifier: Programming Language :: Python :: 3.9
Classifier: Programming Language :: Python :: 3.10
Classifier: Programming Language :: Python :: 3.11
Classifier: Programming Language :: Python :: 3 :: Only
Classifier: Topic :: Utilities
Classifier: Framework :: IPython
Classifier: Framework :: Jupyter :: JupyterLab :: Extensions
Requires-Python: <4,>=3.7
License-File: LICENSE
Requires-Dist: ipython
Requires-Dist: psutil>=5.9.5
Requires-Dist: plantweb
Provides-Extra: dev
Requires-Dist: ipython; extra == "dev"
Requires-Dist: jupyter; extra == "dev"
Requires-Dist: mariadb>=1.0.11; extra == "dev"
Requires-Dist: mariadb-kernel==0.2.0; extra == "dev"
Requires-Dist: sqlparse; extra == "dev"
Provides-Extra: test
Requires-Dist: pytest; extra == "test"
Requires-Dist: coverage; extra == "test"
